drf_test_generator/__init__.py
drf_test_generator/apps.py
drf_test_generator/constants.py
drf_test_generator/py.typed
drf_test_generator/viewset.py
drf_test_generator/management/__init__.py
drf_test_generator/management/commands/__init__.py
drf_test_generator/management/commands/generate_viewset_tests.py
drf_test_generator-0.0.6.dist-info/LICENSE
drf_test_generator-0.0.6.dist-info/METADATA
drf_test_generator-0.0.6.dist-info/WHEEL
drf_test_generator-0.0.6.dist-info/top_level.txt
drf_test_generator-0.0.6.dist-info/RECORD
