Metadata-Version: 2.1
Name: drf-test-generator
Version: 0.0.6
Summary: A Django app to generate basic tests for Django Rest Framework
Home-page: https://github.com/saadmk11/drf-test-generator
Author: Maksudul Haque
Author-email: saad.mk112@gmail.com
License: MIT
Keywords: Django,Django Rest Framework,Testing
Classifier: Development Status :: 3 - Alpha
Classifier: Natural Language :: English
Classifier: Intended Audience :: Developers
Classifier: License :: OSI Approved :: MIT License
Classifier: Operating System :: OS Independent
Classifier: Framework :: Django :: 4.2
Classifier: Framework :: Django :: 5.0
Classifier: Framework :: Django :: 5.1
Classifier: Programming Language :: Python :: 3 :: Only
Classifier: Programming Language :: Python :: 3
Classifier: Programming Language :: Python :: 3.8
Classifier: Programming Language :: Python :: 3.9
Classifier: Programming Language :: Python :: 3.10
Classifier: Programming Language :: Python :: 3.11
Classifier: Programming Language :: Python :: 3.12
Requires-Python: >=3.8
License-File: LICENSE
Requires-Dist: django >=4.2
Requires-Dist: djangorestframework >=3.12
